client/__init__.py
client/__main__.py
client/controller.py
client/model.py
client/utils.py
client/view.py
client/localization/en_US/LC_MESSAGES/messages.mo
client/localization/ru_RU/LC_MESSAGES/messages.mo
common/__init__.py
common/socket.py
common/utility.py
server/__init__.py
server/__main__.py
server/game.py
server/lobby.py
csmsu2020_pong_game-1.1.0.dist-info/METADATA
csmsu2020_pong_game-1.1.0.dist-info/WHEEL
csmsu2020_pong_game-1.1.0.dist-info/entry_points.txt
csmsu2020_pong_game-1.1.0.dist-info/top_level.txt
csmsu2020_pong_game-1.1.0.dist-info/RECORD
