Metadata-Version: 2.1
Name: csmsu2020-pong-game
Version: 1.1.0
Summary: UNKNOWN
Home-page: UNKNOWN
Author: UNKNOWN
Author-email: UNKNOWN
License: UNKNOWN
Platform: UNKNOWN
Requires-Dist: Babel (==2.9.0)
Requires-Dist: Flask (==1.1.2)
Requires-Dist: requests (==2.25.1)
Requires-Dist: setuptools (>=42)
Requires-Dist: wheel
